fastHDMI/__init__.py
fastHDMI/cython_fun.c
fastHDMI/cython_fun.cpython-312-darwin.so
fastHDMI/cython_fun.pyx
fastHDMI/clumping/__init__.py
fastHDMI/clumping/clumping.py
fastHDMI/io/__init__.py
fastHDMI/io/io.py
fastHDMI/mi_estimation/__init__.py
fastHDMI/mi_estimation/mi_estimation.py
fastHDMI/screening/__init__.py
fastHDMI/screening/screening.py
fastHDMI/screening/unified_screening.py
fastHDMI/utils/__init__.py
fastHDMI/utils/data_handling.py
fastHDMI/utils/hardware_detection.py
fastHDMI/utils/utils.py
fasthdmi-1.25.26.dist-info/licenses/LICENSE
fasthdmi-1.25.26.dist-info/METADATA
fasthdmi-1.25.26.dist-info/WHEEL
fasthdmi-1.25.26.dist-info/top_level.txt
fasthdmi-1.25.26.dist-info/RECORD
