Metadata-Version: 2.4
Name: fastHDMI
Version: 1.25.26
Summary: Use fast FFT-based mutual information screening for large datasets. Works well on MRI brain imaging data. Developed by Kai Yang, [GPG Public key Fingerprint: B9F863A56220DBD56B91C3E835022A1A5941D810](https://keys.openpgp.org/vks/v1/by-fingerprint/B9F863A56220DBD56B91C3E835022A1A5941D810)
Home-page: https://github.com/Kaiyangshi-Ito/fastHDMI
Author: Kai Yang
Author-email: Kai Yang <kai.yang2@mail.mcgill.ca>
License: MIT License
Project-URL: Homepage, https://github.com/Kaiyangshi-Ito/fastHDMI
Project-URL: Bug Tracker, https://github.com/Kaiyangshi-Ito/fastHDMI/issues
Classifier: Programming Language :: Python :: 3
Classifier: License :: OSI Approved :: MIT License
Classifier: Operating System :: OS Independent
Requires-Python: >=3.9
License-File: LICENSE
Requires-Dist: numpy>=1.14.2
Requires-Dist: numba>=0.54.1
Requires-Dist: KDEpy>=1.1.12
Requires-Dist: scikit-learn>=1.0.2
Requires-Dist: bed-reader>=1.0.4
Requires-Dist: multiprocess>=0.70.6
Requires-Dist: pandas>=1.4.4
Requires-Dist: dask
Requires-Dist: tqdm>=4.64.1
Requires-Dist: Cython>=0.29.21
Dynamic: author
Dynamic: home-page
Dynamic: license-file
